django_dynamic_formset/__init__.py
django_dynamic_formset-0.0.2.dist-info/METADATA
django_dynamic_formset-0.0.2.dist-info/WHEEL
django_dynamic_formset-0.0.2.dist-info/top_level.txt
django_dynamic_formset-0.0.2.dist-info/RECORD
