Metadata-Version: 2.1
Name: django-dynamic-formset
Version: 0.0.2
Summary: An academic experiment package
Home-page: https://pypi.org/project/django-dynamic-formset/
Author: Guangye Bai
Author-email: 2253637@tongji.edu.cn
License: MIT
Keywords: django,formset,experiment,typosquatting,security
Platform: UNKNOWN
Classifier: Development Status :: 2 - Pre-Alpha
Classifier: Intended Audience :: Developers
Classifier: License :: OSI Approved :: MIT License
Classifier: Programming Language :: Python :: 3
Classifier: Topic :: Software Development :: Libraries
Requires-Python: >=3.6
